pymcap/__init__.py
pymcap/core.py
pymcap-0.2.dist-info/METADATA
pymcap-0.2.dist-info/WHEEL
pymcap-0.2.dist-info/licenses/LICENSE
pymcap-0.2.dist-info/RECORD
