Metadata-Version: 2.3
Name: pymcap
Version: 0.2
Summary: A python package to interact with the MCAP CLI Tool
Author-email: sashank-tirumala <stsashank6@gmail.com>
Requires-Python: >=3.8
Requires-Dist: requests>=2.24.0
